neuropipeline2/__init__.py
neuropipeline2/eeg.py
neuropipeline2/fnirs.py
neuropipeline2/module1.py
neuropipeline2/module2.py
neuropipeline2-0.1.3.dist-info/licenses/LICENSE
neuropipeline2-0.1.3.dist-info/METADATA
neuropipeline2-0.1.3.dist-info/WHEEL
neuropipeline2-0.1.3.dist-info/top_level.txt
neuropipeline2-0.1.3.dist-info/RECORD
